gdrive/gdrive.py
src/gdrive.py
gdrive_utils-0.1.dist-info/METADATA
gdrive_utils-0.1.dist-info/WHEEL
gdrive_utils-0.1.dist-info/top_level.txt
gdrive_utils-0.1.dist-info/RECORD
