Metadata-Version: 2.1
Name: gdrive-utils
Version: 0.1
Summary: Google Drive utilities
Home-page: https://github.com/gaparmar/gdrive
Author: Gaurav Parmar
Author-email: gauravtparmar@gmail.com
License: UNKNOWN
Platform: UNKNOWN
Classifier: Programming Language :: Python :: 3
Classifier: License :: OSI Approved :: MIT License
Classifier: Operating System :: OS Independent
